[
    { "name": "grapefruit-1", "color": "#ed5565" },
    { "name": "grapefruit-2", "color": "#da4453" },
    { "name": "bittersweet-1", "color": "#fc6e51" },
    { "name": "bittersweet-2", "color": "#e9573f" },
    { "name": "sunflower-1", "color": "#ffce54" },
    { "name": "sunflower-2", "color": "#f6bb42" },
    { "name": "grass-1", "color": "#a0d468" },
    { "name": "grass-2", "color": "#8cc152" },
    { "name": "mint-1", "color": "#48cfad" },
    { "name": "mint-2", "color": "#37bc9b" },
    { "name": "aqua-1", "color": "#4fc1e9" },
    { "name": "aqua-2", "color": "#3bafda" },
    { "name": "bluejeans-1", "color": "#5d9cec" },
    { "name": "bluejeans-2", "color": "#4a89dc" },
    { "name": "lavender-1", "color": "#ac92ec" },
    { "name": "lavender-2", "color": "#967adc" },
    { "name": "pinkrose-1", "color": "#ec87c0" },
    { "name": "pinkrose-2", "color": "#d770ad" },
    { "name": "light-gray-1", "color": "#f5f7fa" },
    { "name": "light-gray-2", "color": "#e6e9ed" },
    { "name": "medium-gray-1", "color": "#ccd1d9" },
    { "name": "medium-gray-2", "color": "#aab2bd" },
    { "name": "dark-gray-1", "color": "#656d78" },
    { "name": "dark-gray-2", "color": "#434a54" }
]
